[
    {
        "idx": "1",
        "word": "古いビルだけれど、明治時代を感じさせるデザインで貴重だ",
        "ans": "古いビルだけれど、明治時代を感じさせるデザインで貴重だ",
        "n_ok": "0",
        "n_ng": "0"
    },
    {
        "idx": "2",
        "word": "携帯電話には通話以外の機能もたくさん付いている",
        "ans": "携帯電話には通話以外の機能もたくさん付いている",
        "n_ok": "0",
        "n_ng": "0"
    },
    {
        "idx": "3",
        "word": "生まれたばかりの乳児には、大人の愛情が必要だ",
        "ans": "生まれたばかりの乳児には、大人の愛情が必要だ",
        "n_ok": "0",
        "n_ng": "0"
    },
    {
        "idx": "4",
        "word": "事故防止は事故の原因を把握することから始まる",
        "ans": "事故防止は事故の原因を把握することから始まる",
        "n_ok": "0",
        "n_ng": "0"
    },
    {
        "idx": "5",
        "word": "新しいプロジェクトの5年分の年次計画がたてられた",
        "ans": "新しいプロジェクトの5年分の年次計画がたてられた",
        "n_ok": "0",
        "n_ng": "0"
    },
    {
        "idx": "6",
        "word": "部下から結婚式のスピーチを頼まれた",
        "ans": "部下から結婚式のスピーチを頼まれた",
        "n_ok": "0",
        "n_ng": "0"
    },
    {
        "idx": "7",
        "word": "金融市場は世界経済の影響を強く受ける",
        "ans": "金融市場は世界経済の影響を強く受ける",
        "n_ok": "0",
        "n_ng": "0"
    },
    {
        "idx": "8",
        "word": "家庭で使った水が池に溜まって悪臭が漂っている",
        "ans": "家庭で使った水が池に溜まって悪臭が漂っている",
        "n_ok": "0",
        "n_ng": "0"
    },
    {
        "idx": "9",
        "word": "怪談にはお化けや恐ろしいものが出てくるので、聞くと夏でも涼しくなる",
        "ans": "怪談にはお化けや恐ろしいものが出てくるので、聞くと夏でも涼しくなる",
        "n_ok": "0",
        "n_ng": "0"
    },
    {
        "idx": "10",
        "word": "おばあさんがバスに乗ろうとしたら、若者が優しく手を差し出した",
        "ans": "おばあさんがバスに乗ろうとしたら、若者が優しく手を差し出した",
        "n_ok": "0",
        "n_ng": "0"
    }
]